sphereob/__init__.py
sphereob/resources.py
sphereob/sphere_main.py
sphereob/sphere_response.py
sphere_response_package-1.5.0.dist-info/METADATA
sphere_response_package-1.5.0.dist-info/WHEEL
sphere_response_package-1.5.0.dist-info/entry_points.txt
sphere_response_package-1.5.0.dist-info/top_level.txt
sphere_response_package-1.5.0.dist-info/RECORD
